mistral_gradio/__init__.py
mistral_gradio-0.0.2.dist-info/METADATA
mistral_gradio-0.0.2.dist-info/WHEEL
mistral_gradio-0.0.2.dist-info/RECORD
