Metadata-Version: 2.3
Name: mistral-gradio
Version: 0.0.2
Summary: A Python package for creating Gradio applications with Mistral models
Project-URL: homepage, https://github.com/AK391/mistral-gradio
Project-URL: repository, https://github.com/AK391/mistral-gradio
Author-email: AK <ahsen.khaliq@gmail.com>
Classifier: License :: OSI Approved :: MIT License
Classifier: Operating System :: OS Independent
Classifier: Programming Language :: Python :: 3
Requires-Python: >=3.10
Requires-Dist: gradio>=5.5.0
Requires-Dist: mistralai
Provides-Extra: dev
Requires-Dist: pytest; extra == 'dev'
